[
   {
      "authors" : [
         "萩行 正嗣"
      ],
      "date" : "2016-03",
      "publised" : "言語処理学会第22回年次大会発表論文集",
      "title" : "選択式天気情報を用いたソーシャルメディアからの有用投稿抽出",
      "type" : "INPROCEEDINGS",
      "award" : null
   },
   {
      "authors" : [
         "朝倉 康伸",
         "萩行 正嗣",
         "小町 守"
      ],
      "date" : "2016-03",
      "publised" : "言語処理学会第22回年次大会発表論文集",
      "title" : "マイクロブログにおける浸水害情報の解析",
      "type" : "INPROCEEDINGS",
      "award" : null
   },
   {
      "authors" : [
         "萩行 正嗣",
         "河原 大輔",
         "黒橋 禎夫"
      ],
      "date" : "2014-03",
      "publised" : "言語処理学会第20回年次大会発表論文集",
      "title" : "著者・読者表現および外界ゼロ照応を考慮したゼロ照応解析",
      "type" : "INPROCEEDINGS",
      "award" : null
   },
   {
      "authors" : [
         "萩行 正嗣",
         "河原 大輔",
         "黒橋 禎夫"
      ],
      "date" : "2012-05",
      "publised" : "研究報告自然言語処理(NL206)",
      "title" : "多様な文書の書き始めに対する意味関係タグ付きコーパスの構築",
      "type" : "INPROCEEDINGS",
      "award" : null
   },
   {
      "authors" : [
         "萩行 正嗣",
         "黒橋 禎夫"
      ],
      "date" : "2011-03",
      "publised" : "言語処理学会第17回年次大会発表論文集",
      "title" : "構造化した属性表現に基づく国語辞典定義文の漸進的解釈",
      "type" : "INPROCEEDINGS",
      "award" : null
   },
   {
      "authors" : [
         "萩行 正嗣",
         "黒橋 禎夫"
      ],
      "date" : "2009-03",
      "publised" : "言語処理学会第15回年次大会発表論文集",
      "title" : "辞書定義文を用いた二字漢語の言い換え表現の生成",
      "type" : "INPROCEEDINGS",
      "award" : null
   },
   {
      "authors" : [
         "萩行 正嗣",
         "柴田 知秀",
         "黒橋 禎夫"
      ],
      "date" : "2008-05",
      "publised" : "情報処理学会研究報告自然言語処理(NL185)",
      "title" : "表層・語彙的特徴量に基づくブログの面白さ分析",
      "type" : "INPROCEEDINGS",
      "award" : "学生奨励賞受賞"
   }
]
