[
   {
      "authors" : [
         "Yasunobu Asakura",
         "Masatsugu Hangyo",
         "Mamoru Komachi"
      ],
      "date" : "2016-00",
      "pdf" : null,
      "publised" : "Proceedings of the 2nd Workshop on Noisy User-generated Text (WNUT)",
      "title" : "Disaster Analysis using User-Generated Weather Report",
      "type" : "INPROCEEDINGS",
      "award" : null
   },
   {
      "authors" : [
         "Masatsugu Hangyo",
         "Daisuke Kawahara",
         "Sadao Kurohashi"
      ],
      "date" : "2013-10",
      "pdf" : "http://www.aclweb.org/anthology/D13-1095",
      "publised" : "The 2013 Conference on Empirical Methods on Natural Language Processing (EMNLP2013)",
      "title" : "Japanese Zero Reference Resolution Considering Exophora and Author/Reader Mentions.",
      "type" : "INPROCEEDINGS",
      "award" : null
   },
   {
      "authors" : [
         "Masatsugu Hangyo",
         "Daisuke Kawahara",
         "Sadao Kurohashi"
      ],
      "date" : "2012-11",
      "pdf" : "http://www.aclweb.org/anthology/Y12-1058",
      "publised" : "Proceedings of the 26th Pacific Asia Conference on Language, Information, and Computation (PACLIC2012)",
      "title" : "Building a diverse document leads corpus annotated with semantic relations",
      "type" : "INPROCEEDINGS",
      "award" : null
   }
]
